epcdltranslator/__init__.py
epcdltranslator-1.0.0.dist-info/LICENSE
epcdltranslator-1.0.0.dist-info/METADATA
epcdltranslator-1.0.0.dist-info/WHEEL
epcdltranslator-1.0.0.dist-info/top_level.txt
epcdltranslator-1.0.0.dist-info/RECORD
