Metadata-Version: 2.1
Name: epcdltranslator
Version: 1.0.0
Summary: Translates EPC URIs and EPC Class URIs into their canonical GS1 Digital Link URI equivalents.
Home-page: https://github.com/RalphTro/gs1-epc-digitallink-translator
Author: Ralph Troeger
Author-email: ralph.troeger@gmail.com
License: UNKNOWN
Platform: UNKNOWN
Classifier: Programming Language :: Python :: 3
Classifier: License :: OSI Approved :: MIT License
Classifier: Operating System :: OS Independent
Requires-Python: >=3.7
